destrys_uv_example_lib/__init__.py
destrys_uv_example_lib/py.typed
destrys_uv_example_lib-0.1.0.dist-info/METADATA
destrys_uv_example_lib-0.1.0.dist-info/WHEEL
destrys_uv_example_lib-0.1.0.dist-info/RECORD
