Metadata-Version: 2.4
Name: destrys-uv-example-lib
Version: 0.1.0
Summary: Add your description here
Author-email: destrys <destrys@gmail.com>
Requires-Python: >=3.9
Requires-Dist: astropy>=6.0.1
Requires-Dist: tensorflow>=2.19.0
Requires-Dist: torch>=2.7.1
